{"stats":{"minecraft:dropped":{"minecraft:bread":25,"minecraft:wheat_seeds":12,"minecraft:oak_log":33,"minecraft:stick":14},"minecraft:used":{"minecraft:wheat_seeds":189,"minecraft:acacia_boat":8,"minecraft:water_bucket":7,"minecraft:iron_ore":1,"minecraft:acacia_log":5,"minecraft:stone_shovel":52,"minecraft:stone_pickaxe":681,"minecraft:cartography_table":1,"minecraft:chest":6,"minecraft:cobblestone_slab":17,"minecraft:sugar_cane":8,"minecraft:stone_hoe":2,"minecraft:torch":72,"minecraft:dirt":7,"minecraft:crafting_table":3,"minecraft:red_bed":17,"minecraft:white_bed":1,"minecraft:granite":2,"minecraft:glass":23,"minecraft:lava_bucket":2,"minecraft:iron_pickaxe":82,"minecraft:bread":12,"minecraft:map":1,"minecraft:iron_door":1,"minecraft:gravel":3,"minecraft:acacia_fence_gate":6,"minecraft:stone_axe":25,"minecraft:cobblestone":73,"minecraft:furnace":1,"minecraft:andesite":29,"minecraft:acacia_fence":22,"minecraft:bucket":8,"minecraft:acacia_planks":12,"minecraft:light_gray_bed":7},"minecraft:broken":{"minecraft:stone_pickaxe":5},"minecraft:custom":{"minecraft:interact_with_furnace":3,"minecraft:animals_bred":16,"minecraft:interact_with_crafting_table":35,"minecraft:interact_with_cartography_table":24,"minecraft:play_one_minute":207237,"minecraft:leave_game":13,"minecraft:time_since_death":207237,"minecraft:sleep_in_bed":15,"minecraft:climb_one_cm":132978,"minecraft:time_since_rest":2080,"minecraft:sprint_one_cm":333411,"minecraft:damage_taken":60,"minecraft:walk_one_cm":647313,"minecraft:drop":14,"minecraft:damage_dealt":50,"minecraft:swim_one_cm":12654,"minecraft:talked_to_villager":13,"minecraft:fly_one_cm":45474,"minecraft:open_chest":70,"minecraft:crouch_one_cm":6182,"minecraft:sneak_time":3762,"minecraft:walk_under_water_one_cm":39844,"minecraft:boat_one_cm":627694,"minecraft:jump":1080,"minecraft:walk_on_water_one_cm":69564,"minecraft:fall_one_cm":5133},"minecraft:picked_up":{"minecraft:wheat":119,"minecraft:crafting_table":2,"minecraft:andesite":33,"minecraft:smoker":1,"minecraft:flint":5,"minecraft:oak_log":33,"minecraft:acacia_boat":9,"minecraft:red_bed":17,"minecraft:paper":5,"minecraft:dirt":14,"minecraft:acacia_planks":1,"minecraft:kelp":4,"minecraft:stonecutter":1,"minecraft:wheat_seeds":416,"minecraft:iron_ore":96,"minecraft:cobblestone_slab":48,"minecraft:light_gray_wool":6,"minecraft:sugar_cane":355,"minecraft:melon_slice":55,"minecraft:chest":4,"minecraft:furnace":1,"minecraft:stick":14,"minecraft:acacia_fence":6,"minecraft:torch":25,"minecraft:gravel":48,"minecraft:sand":35,"minecraft:diorite":26,"minecraft:gold_ore":6,"minecraft:redstone":261,"minecraft:light_gray_bed":5,"minecraft:diamond":5,"minecraft:hay_block":49,"minecraft:granite":21,"minecraft:bread":9,"minecraft:coal":81,"minecraft:white_wool":3,"minecraft:cobblestone":483},"minecraft:mined":{"minecraft:diamond_ore":5,"minecraft:glass_pane":2,"minecraft:farmland":1,"minecraft:red_bed":17,"minecraft:melon_stem":1,"minecraft:smoker":1,"minecraft:crafting_table":2,"minecraft:torch":4,"minecraft:granite":21,"minecraft:melon":12,"minecraft:chest":4,"minecraft:light_gray_bed":5,"minecraft:tall_grass":1,"minecraft:cobblestone":33,"minecraft:sugar_cane":269,"minecraft:diorite":26,"minecraft:wall_torch":15,"minecraft:hay_block":50,"minecraft:redstone_ore":59,"minecraft:furnace":1,"minecraft:iron_ore":96,"minecraft:wheat":187,"minecraft:andesite":38,"minecraft:grass":5,"minecraft:coal_ore":81,"minecraft:cobblestone_slab":1,"minecraft:acacia_fence":6,"minecraft:gravel":55,"minecraft:dirt":13,"minecraft:acacia_planks":1,"minecraft:stonecutter":1,"minecraft:stone":391,"minecraft:gold_ore":6},"minecraft:crafted":{"minecraft:coal_block":2,"minecraft:cobblestone_slab":60,"minecraft:oak_planks":16,"minecraft:stone_shovel":1,"minecraft:map":1,"minecraft:acacia_fence_gate":5,"minecraft:stone":39,"minecraft:bread":51,"minecraft:cartography_table":1,"minecraft:light_gray_bed":2,"minecraft:paper":63,"minecraft:ladder":27,"minecraft:stick":128,"minecraft:iron_ingot":62,"minecraft:stone_pickaxe":5,"minecraft:chest":4,"minecraft:white_bed":1,"minecraft:acacia_fence":18,"minecraft:iron_door":3,"minecraft:acacia_planks":224,"minecraft:stone_hoe":1,"minecraft:wheat":18}},"DataVersion":2586}